CHANGES.rst
MANIFEST.in
README.rst
README.txt
buildout.cfg
setup.cfg
setup.py
collective/__init__.py
collective.editskinswitcher.egg-info/PKG-INFO
collective.editskinswitcher.egg-info/SOURCES.txt
collective.editskinswitcher.egg-info/dependency_links.txt
collective.editskinswitcher.egg-info/entry_points.txt
collective.editskinswitcher.egg-info/namespace_packages.txt
collective.editskinswitcher.egg-info/not-zip-safe
collective.editskinswitcher.egg-info/requires.txt
collective.editskinswitcher.egg-info/top_level.txt
collective/editskinswitcher/__init__.py
collective/editskinswitcher/config.py
collective/editskinswitcher/configure.zcml
collective/editskinswitcher/monkeypatches.py
collective/editskinswitcher/permissions.py
collective/editskinswitcher/profiles.zcml
collective/editskinswitcher/rebuild_i18n.sh
collective/editskinswitcher/skin.py
collective/editskinswitcher/testing-skins.zcml
collective/editskinswitcher/testing.zcml
collective/editskinswitcher/traversal.py
collective/editskinswitcher/upgrades.py
collective/editskinswitcher/utils.py
collective/editskinswitcher/browser/__init__.py
collective/editskinswitcher/browser/configure.zcml
collective/editskinswitcher/browser/document_preview.py
collective/editskinswitcher/browser/interfaces.py
collective/editskinswitcher/browser/menu.py
collective/editskinswitcher/browser/view.py
collective/editskinswitcher/browser/viewlets.py
collective/editskinswitcher/browser/templates/iframe.js
collective/editskinswitcher/browser/templates/mutate_skin.js
collective/editskinswitcher/browser/templates/preview_view.pt
collective/editskinswitcher/browser/templates/preview_viewlet.pt
collective/editskinswitcher/browser/templates/select_skin.pt
collective/editskinswitcher/locales/editskinswitcher.pot
collective/editskinswitcher/locales/en/LC_MESSAGES/editskinswitcher.mo
collective/editskinswitcher/locales/en/LC_MESSAGES/editskinswitcher.po
collective/editskinswitcher/locales/nl/LC_MESSAGES/editskinswitcher.mo
collective/editskinswitcher/locales/nl/LC_MESSAGES/editskinswitcher.po
collective/editskinswitcher/profiles/default/jsregistry.xml
collective/editskinswitcher/profiles/default/metadata.xml
collective/editskinswitcher/profiles/default/propertiestool.xml
collective/editskinswitcher/tests/__init__.py
collective/editskinswitcher/tests/add_preview.py
collective/editskinswitcher/tests/base.py
collective/editskinswitcher/tests/browser.py
