Metadata-Version: 1.1
Name: collective.editskinswitcher
Version: 3.2
Summary: Switch to the edit skin for certain domains.
Home-page: https://github.com/collective/collective.editskinswitcher
Author: Maurits van Rees
Author-email: m.van.rees@zestsoftware.nl
License: GPL
Platform: UNKNOWN
Classifier: Framework :: Plone
Classifier: Framework :: Plone :: 4.1
Classifier: Framework :: Plone :: 4.2
Classifier: Framework :: Plone :: 4.3
Classifier: Framework :: Zope2
Classifier: Programming Language :: Python
Classifier: Programming Language :: Python :: 2.6
Classifier: Programming Language :: Python :: 2.7
Classifier: Topic :: Software Development :: Libraries :: Python Modules
